st_link_analysis_ie2/__init__.py
st_link_analysis_ie2/component/__init__.py
st_link_analysis_ie2/component/component.py
st_link_analysis_ie2/component/events.py
st_link_analysis_ie2/component/icons.py
st_link_analysis_ie2/component/layouts.py
st_link_analysis_ie2/component/styles.py
st_link_analysis_ie2/frontend/build/32b01d6a21d9433a251c.ttf
st_link_analysis_ie2/frontend/build/apache-arrow.6795ba5a5a6f1b4c9100.bundle.js
st_link_analysis_ie2/frontend/build/cytoscape.f552fc7815336b8b176e.bundle.js
st_link_analysis_ie2/frontend/build/cytoscape.f552fc7815336b8b176e.bundle.js.LICENSE.txt
st_link_analysis_ie2/frontend/build/index.4154a23e7376b75c64c7.bundle.js
st_link_analysis_ie2/frontend/build/index.html
st_link_analysis_ie2/frontend/build/runtime.f45e30ba52052b8fb0c1.bundle.js
st_link_analysis_ie2/frontend/build/streamlit-component-lib.a45f9d47188ad6ed597f.bundle.js
st_link_analysis_ie2/frontend/build/vendors.19de8d7b23d1a57d52fd.bundle.js
st_link_analysis_ie2/frontend/build/vendors.19de8d7b23d1a57d52fd.bundle.js.LICENSE.txt
st_link_analysis_ie2/frontend/build/icons/123.svg
st_link_analysis_ie2/frontend/build/icons/account_balance.svg
st_link_analysis_ie2/frontend/build/icons/alternate_email.svg
st_link_analysis_ie2/frontend/build/icons/badge.svg
st_link_analysis_ie2/frontend/build/icons/business.svg
st_link_analysis_ie2/frontend/build/icons/calendar.svg
st_link_analysis_ie2/frontend/build/icons/cell_tower.svg
st_link_analysis_ie2/frontend/build/icons/chat.svg
st_link_analysis_ie2/frontend/build/icons/cloud.svg
st_link_analysis_ie2/frontend/build/icons/concept.svg
st_link_analysis_ie2/frontend/build/icons/contract.svg
st_link_analysis_ie2/frontend/build/icons/credit_card.svg
st_link_analysis_ie2/frontend/build/icons/description.svg
st_link_analysis_ie2/frontend/build/icons/directions_car.svg
st_link_analysis_ie2/frontend/build/icons/dns.svg
st_link_analysis_ie2/frontend/build/icons/email.svg
st_link_analysis_ie2/frontend/build/icons/flag.svg
st_link_analysis_ie2-0.3.5.dist-info/LICENSE
st_link_analysis_ie2-0.3.5.dist-info/METADATA
st_link_analysis_ie2-0.3.5.dist-info/WHEEL
st_link_analysis_ie2-0.3.5.dist-info/top_level.txt
st_link_analysis_ie2-0.3.5.dist-info/RECORD
