Metadata-Version: 2.1
Name: st_link_analysis_ie2
Version: 0.3.5
Summary: A streamlit custom component for visualizing and interacting with graphs
Author: AlrasheedA, Dylan Lau
License: MIT
Project-URL: Homepage, https://github.com/AlrasheedA/st-link-analysis
Project-URL: Issues, https://github.com/AlrasheedA/st-link-analysis/issues
Keywords: streamlit,cytoscape,graph,link analysis
Classifier: Programming Language :: Python :: 3
Classifier: License :: OSI Approved :: MIT License
Classifier: Operating System :: OS Independent
Requires-Python: >=3.8
License-File: LICENSE
Requires-Dist: streamlit>=0.63
Provides-Extra: dev
Requires-Dist: ruff; extra == "dev"
Requires-Dist: pytest; extra == "dev"
